LICENSE
README.md
pyproject.toml
setup.cfg
setup.py
archipel_utils/__init__.py
archipel_utils/data.py
archipel_utils/msg.py
archipel_utils/path.py
archipel_utils/process.py
archipel_utils.egg-info/PKG-INFO
archipel_utils.egg-info/SOURCES.txt
archipel_utils.egg-info/dependency_links.txt
archipel_utils.egg-info/requires.txt
archipel_utils.egg-info/top_level.txt