Metadata-Version: 2.1
Name: archipel-utils
Version: 0.1.7
Summary: Small utils for Archipel plateform
Home-page: https://github.com/alpineintuition/archipel-utils
Author: alpineintuition
Author-email: contact@alpineintuition.ch
License: Apache License 2.0
Download-URL: https://github.com/alpineintuition/archipel-utils/archive/v0.1.7.tar.gz
Keywords: archipel-utils,archipel
Platform: UNKNOWN
License-File: LICENSE
